README.md
cmdr/_version.py
cmdr/datamodel/__init__.py
cmdr/datamodel/cmdr.py
cmdr/schema/cmdr.yaml
cmdr-0.1.0.dist-info/LICENSE
cmdr-0.1.0.dist-info/METADATA
cmdr-0.1.0.dist-info/WHEEL
cmdr-0.1.0.dist-info/RECORD
