Metadata-Version: 2.1
Name: cmdr
Version: 0.1.0
Summary: Core Model for Data Research (Tentative)
License: MIT
Author: My Name
Author-email: my-name@my-org.org
Requires-Python: >=3.9,<4.0
Classifier: License :: OSI Approved :: MIT License
Classifier: Programming Language :: Python :: 3
Classifier: Programming Language :: Python :: 3.9
Classifier: Programming Language :: Python :: 3.10
Classifier: Programming Language :: Python :: 3.11
Classifier: Programming Language :: Python :: 3.12
Provides-Extra: docs
Requires-Dist: SQLAlchemy (>=1.4.32,<2.0.0,!=1.4.46)
Requires-Dist: linkml-runtime (>=1.1.24,<2.0.0)
Requires-Dist: linkml-transformer (>=0.1,<0.2)
